LICENSE
README.md
setup.py
steam_inventory/inventories.py
steam_inventory.egg-info/PKG-INFO
steam_inventory.egg-info/SOURCES.txt
steam_inventory.egg-info/dependency_links.txt
steam_inventory.egg-info/requires.txt
steam_inventory.egg-info/top_level.txt